panda_pos_api/__init__.py
panda_pos_api/graphql_query_builder.py
panda_pos_api/main.py
panda_pos_api/models/Product.py
panda_pos_api/models/Ticket.py
panda_pos_api/models/__init__.py
pandapos_api-1.0.2.dist-info/METADATA
pandapos_api-1.0.2.dist-info/WHEEL
pandapos_api-1.0.2.dist-info/top_level.txt
pandapos_api-1.0.2.dist-info/RECORD
