Metadata-Version: 2.1
Name: pandapos-api
Version: 1.0.2
Summary: PandaPos API
Author: Esat
Author-email: esatyilmaz3500@gmail.com
